ansible_taskrunner/__init__.py
ansible_taskrunner/cli.py
ansible_taskrunner/config.py
ansible_taskrunner/defaults.py
ansible_taskrunner/logger.py
ansible_taskrunner/setup.cx_freeze.py
ansible_taskrunner/files/start-tutorial.bat
ansible_taskrunner/files/tasks-console.bat
ansible_taskrunner/files/cfg/default.ini
ansible_taskrunner/files/macros/default.mac
ansible_taskrunner/libs/__init__.py
ansible_taskrunner/libs/bastion_mode/__init__.py
ansible_taskrunner/libs/cli/__init__.py
ansible_taskrunner/libs/cli/click_commands_create_group.py
ansible_taskrunner/libs/cli/click_commands_create_init.py
ansible_taskrunner/libs/cli/click_commands_create_sub.py
ansible_taskrunner/libs/cli/click_commands_init_sub.py
ansible_taskrunner/libs/cli/invocation.py
ansible_taskrunner/libs/click_extras/__init__.py
ansible_taskrunner/libs/click_extras/help.py
ansible_taskrunner/libs/click_extras/options_advanced.py
ansible_taskrunner/libs/errorhandler/__init__.py
ansible_taskrunner/libs/formatting/__init__.py
ansible_taskrunner/libs/help/__init__.py
ansible_taskrunner/libs/language/__init__.py
ansible_taskrunner/libs/language/en.yaml
ansible_taskrunner/libs/logger/__init__.py
ansible_taskrunner/libs/proc_mgmt/__init__.py
ansible_taskrunner/libs/providers/__init__.py
ansible_taskrunner/libs/providers/ansible.py
ansible_taskrunner/libs/providers/bash.py
ansible_taskrunner/libs/providers/vagrant.py
ansible_taskrunner/libs/sshutil/__init__.py
ansible_taskrunner/libs/sshutil/client.py
ansible_taskrunner/libs/sshutil/scp.py
ansible_taskrunner/libs/sshutil/sync.py
ansible_taskrunner/plugins/__init__.py
tests/__init__.py
tests/test_ansible_taskrunner.py
ansible_taskrunner-2.11.0.dist-info/METADATA
ansible_taskrunner-2.11.0.dist-info/WHEEL
ansible_taskrunner-2.11.0.dist-info/entry_points.txt
ansible_taskrunner-2.11.0.dist-info/top_level.txt
ansible_taskrunner-2.11.0.dist-info/RECORD
