Metadata-Version: 2.1
Name: ansible-taskrunner
Version: 2.11.0
Summary: Ansible Task Runner
Home-page: https://github.com/berttejeda/ansible-taskrunner.git
Author: Engelbert Tejeda
Author-email: etejeda@tecknicos.com
Keywords: ansible,playbook,wrapper,bash,python,click,task-runner,subprocess,yaml,cli,options
Classifier: Development Status :: 3 - Alpha
Classifier: Intended Audience :: Developers
Classifier: Intended Audience :: Information Technology
Classifier: License :: OSI Approved :: MIT License
Classifier: Natural Language :: English
Classifier: Programming Language :: Python :: 2.7
Classifier: Programming Language :: Python :: 3
Classifier: Programming Language :: Python :: 3.4
Classifier: Programming Language :: Python :: 3.5
Classifier: Programming Language :: Python :: 3.6
Classifier: Programming Language :: Python :: 3.7
Classifier: Programming Language :: Python :: 3.10
Requires-Python: >=2.7
Requires-Dist: btconfig (<5.0.0,>=4.4.0)
Requires-Dist: click (<9.0.0,>=8.1.3)
Requires-Dist: colorama (==0.4.3)
Requires-Dist: coloredlogs (<16.0.0,>=15.0.0)
Requires-Dist: PyYAML (<7.0,>=6.0)
Requires-Dist: paramiko (==2.10.1) ; sys_platform == "win32" or sys_platform == "cygwin"
Provides-Extra: tests
Requires-Dist: pytest ; extra == 'tests'
Requires-Dist: pytest-cov ; extra == 'tests'
Requires-Dist: coveralls ; extra == 'tests'
Requires-Dist: flake8 ; extra == 'tests'
Requires-Dist: mypy ; extra == 'tests'
